Metadata-Version: 2.1
Name: ai-edge-litert-sdk-mediatek
Version: 0.1.0
Summary: MediaTek NeuroPilot SDK for AI Edge LiteRT
Home-page: https://www.tensorflow.org/lite/
Author: Google AI Edge Authors
Author-email: packages@tensorflow.org
License: Apache 2.0
Keywords: litert tflite tensorflow tensor machine learning
Classifier: Development Status :: 5 - Production/Stable
Classifier: Intended Audience :: Developers
Classifier: Intended Audience :: Education
Classifier: Intended Audience :: Science/Research
Classifier: License :: OSI Approved :: Apache Software License
Classifier: Programming Language :: Python :: 3
Classifier: Programming Language :: Python :: 3.8
Classifier: Programming Language :: Python :: 3.9
Classifier: Programming Language :: Python :: 3.10
Classifier: Programming Language :: Python :: 3.11
Classifier: Topic :: Scientific/Engineering
Classifier: Topic :: Scientific/Engineering :: Mathematics
Classifier: Topic :: Scientific/Engineering :: Artificial Intelligence
Classifier: Topic :: Software Development
Classifier: Topic :: Software Development :: Libraries
Classifier: Topic :: Software Development :: Libraries :: Python Modules
